vxghpages-0.2.0.dist-info/top_level.txt
vxghpages-0.2.0.dist-info/METADATA
vxghpages-0.2.0.dist-info/DESCRIPTION.rst
vxghpages-0.2.0.dist-info/metadata.json
vxghpages-0.2.0.dist-info/WHEEL
vxghpages-0.2.0.dist-info/entry_points.txt
vxghpages-0.2.0.dist-info/RECORD
vxghpages/__init__.py
vxghpages/creator.py~
vxghpages/cli.py~
vxghpages/__main__.py
vxghpages/Makefile.template~
vxghpages/Makefile.template
vxghpages/creator.py
vxghpages/cli.py
